{
  "tab_title_profile": "KSVG | 帳戶管理",
  "text_authenticating": "正在驗證安全憑證...",
  "profile_title": "帳戶管理",
  "profile_subtitle": "管理您的個人資料及組織公開資訊。",
  "sec_personal": "基本身份與安全",
  "sec_org": "組織展示資訊",
  "label_email": "安全驗證郵箱 (不可修改)",
  "label_name": "顯示姓名",
  "label_student_id": "學號 (Student ID)",
  "label_phone": "聯絡電話",
  "label_dept": "所屬部門 (Department)",
  "label_position": "職位 (Position)",
  "label_portfolio": "個人作品集 / 社交主頁連結",
  "label_bio": "個人簡介 (Short Bio)",
  "btn_save": "儲存更改",
  "btn_cancel": "取消返回",
  "alert_success": "資料更新成功！",
  "alert_error": "更新失敗，請稍後重試或聯絡支援。",
  "auth_sign_out": "登出帳戶",
  "auth_logged_in_as": "當前登入帳號："
}