{
  "tab_title_partners": "KSVG | 合作单位",
  "partners_page_title": "合作单位",
  "partners_page_subtitle": "感谢以下校内外组织与 KSVG 建立协作关系，共同推动校园视觉媒体发展",
  "partner_bkc_name": "康桥银行",
  "partner_bkc_desc": "康桥学生自主运营的校园金融机构，提供创新金融教育与服务体验",
  "partner_kcsc_name": "昆山康桥学生会公关组",
  "partner_kcsc_desc": "负责学生会对外联络与形象宣传的核心部门",
  "partner_kcva_name": "康桥排球联赛",
  "partner_kcva_desc": "KCVA — 康桥排球联赛，推动校园排球运动发展，组织校内联赛与校际交流",
  "partner_vb_name": "康桥排球协会",
  "partner_vb_desc": "推动校园排球运动发展，组织校内联赛与校际交流",
  "partner_hr_name": "地平线追梦之巅",
  "partner_hr_desc": "追逐速度与创新的学生赛车工程团队，挑战极限、探索未来",
  "partner_visit_website": "访问网站",
  "partner_link_pending": "链接待更新",
  "auth_settings": "信息设置",
  "auth_sign_out": "注销退出"
}